{"skeleton":{"hash":"t4GBvFpLtfvL+D0u8vwkuE7yl7I","spine":"3.8.94","x":-114.99,"y":-89.53,"width":204.98,"height":218.43,"images":"../ForCreature/Snails/","audio":"C:/Users/BaekSeongYeol/Desktop/spineAssets"},"bones":[{"name":"root"},{"name":"Body","parent":"root","length":159.33,"rotation":178.3,"x":83.36,"y":-4.38},{"name":"Mouse","parent":"Body","length":37.17,"rotation":-82.44,"x":150.62,"y":-2.13}],"slots":[{"name":"Basic/Basic_body","bone":"Body","attachment":"Wing"},{"name":"Basic/Basic_mouse","bone":"Mouse","attachment":"Basic_mouse"}],"skins":[{"name":"default","attachments":{"Basic/Basic_body":{"Wing":{"x":96.53,"y":-21.2,"scaleX":0.8401,"scaleY":0.8401,"rotation":-178.3,"width":244,"height":260}},"Basic/Basic_mouse":{"Basic_mouse":{"x":10.66,"y":0.62,"rotation":-95.86,"width":28,"height":27}}}}],"animations":{"Eat":{"bones":{"Mouse":{"translate":[{"curve":"stepped"},{"time":0.3333,"x":-0.28,"y":9.34,"curve":"stepped"},{"time":0.6667}],"scale":[{"curve":"stepped"},{"time":0.3333,"x":1.533,"curve":"stepped"},{"time":0.6667}]}}},"Play":{"bones":{"Body":{"rotate":[{"curve":"stepped"},{"time":0.3333,"angle":-5.24,"curve":"stepped"},{"time":0.6667}]}}},"stand":{"bones":{"Body":{"translate":[{"curve":"stepped"},{"time":0.3333,"x":9.1,"curve":"stepped"},{"time":0.6667}],"scale":[{"curve":"stepped"},{"time":0.3333,"x":1.043,"curve":"stepped"},{"time":0.6667}]}}}}}